Metadata-Version: 2.1
Name: ZMusicLibrary
Version: 1.0.6
Summary: An extremely easy way to create notes, intervals, chords, and scales! Save yourself the trouble of music theory!
Home-page: https://github.com/ZSchweyk/MusicLibrary
Author: Zeyn Schweyk
Author-email: zschweyk@gmail.com
License: MIT
Download-URL: https://github.com/ZSchweyk/ZMusicLibrary/archive/refs/tags/v1.0.6.tar.gz
Project-URL: Portfolio Description, https://2022mechatronicszeynschweyk.weebly.com/senior_year_capstone
Keywords: notes,intervals,chords,scales,custom,pre-defined,music,piano
Platform: UNKNOWN
Classifier: Development Status :: 5 - Production/Stable
Classifier: Intended Audience :: Developers
Classifier: Topic :: Software Development :: Build Tools
Classifier: License :: OSI Approved :: MIT License
Classifier: Operating System :: OS Independent
Classifier: Programming Language :: Python :: 3
Requires-Python: >=3.6
License-File: LICENSE.txt
